dystrack/__init__.py
dystrack/manager/__init__.py
dystrack/manager/cmdline.py
dystrack/manager/manager.py
dystrack/manager/transmitters.py
dystrack/pipelines/__init__.py
dystrack/pipelines/center_of_mass.py
dystrack/pipelines/chick_node.py
dystrack/pipelines/lateral_line.py
dystrack/pipelines/utilities/__init__.py
dystrack/pipelines/utilities/constraints.py
dystrack/pipelines/utilities/loading.py
dystrack-1.0.1.dist-info/licenses/LICENSE
dystrack-1.0.1.dist-info/METADATA
dystrack-1.0.1.dist-info/WHEEL
dystrack-1.0.1.dist-info/top_level.txt
dystrack-1.0.1.dist-info/RECORD
