Metadata-Version: 2.4
Name: dystrack
Version: 1.0.1
Summary: Microscope automation for dynamic sample tracking.
Author-email: Jonas Hartmann <jonas.hartmann@ucl.ac.uk>, Zimeng Wu <zimeng.wu.18@ucl.ac.uk>
License-Expression: MIT
Project-URL: homepage, https://whoisjack.github.io/DySTrack/
Project-URL: source, https://github.com/WhoIsJack/DySTrack
Project-URL: documentation, https://whoisjack.github.io/DySTrack/
Project-URL: issues, https://github.com/WhoIsJack/DySTrack/issues
Classifier: Topic :: Scientific/Engineering :: Image Processing
Classifier: Programming Language :: Python :: 3.10
Classifier: Programming Language :: Python :: 3.11
Classifier: Programming Language :: Python :: 3.12
Classifier: Programming Language :: Python :: 3.13
Classifier: Operating System :: Microsoft :: Windows
Requires-Python: <3.14,>=3.10
License-File: LICENSE
Requires-Dist: numpy>=1.24
Requires-Dist: scipy>=1.10
Requires-Dist: matplotlib>=3.7
Requires-Dist: scikit-image>=0.24.0
Requires-Dist: bioio>=3.0.0
Requires-Dist: bioio-tifffile>=1.3.0
Requires-Dist: bioio-czi>=2.4.0
Requires-Dist: bioio-nd2>=1.5.0
Provides-Extra: test
Requires-Dist: pytest; extra == "test"
Requires-Dist: pytest-mock; extra == "test"
Requires-Dist: pytest-cov; extra == "test"
Requires-Dist: coverage; extra == "test"
Requires-Dist: fake-winreg; extra == "test"
Provides-Extra: dev
Requires-Dist: jupyter; extra == "dev"
Requires-Dist: ipykernel; extra == "dev"
Requires-Dist: black[jupyter]; extra == "dev"
Requires-Dist: isort; extra == "dev"
Provides-Extra: docs
Requires-Dist: sphinx; extra == "docs"
Requires-Dist: nbsphinx; extra == "docs"
Requires-Dist: pydata-sphinx-theme; extra == "docs"
Requires-Dist: sphinx-toolbox; extra == "docs"
Provides-Extra: full
Requires-Dist: dystrack[dev,docs,test]; extra == "full"
Dynamic: license-file
